citygan/__init__.py
citygan/citygan.py
citygan/citygan_util.py
citygan/gui.py
citygan/pix2pix_citygenerator.py
citygan/threaded_gui.py
citygan-0.1.6.dist-info/LICENSE.txt
citygan-0.1.6.dist-info/METADATA
citygan-0.1.6.dist-info/WHEEL
citygan-0.1.6.dist-info/top_level.txt
citygan-0.1.6.dist-info/RECORD
